extinfo/__init__.py
extinfo/cli.py
extinfo/exceptions.py
extinfo/extractors/__init__.py
extinfo/extractors/fileinfo_com.py
extinfo/extractors/filesuffix_com.py
extinfo/utils.py
extinfo-0.0.8.dist-info/LICENSE
extinfo-0.0.8.dist-info/METADATA
extinfo-0.0.8.dist-info/WHEEL
extinfo-0.0.8.dist-info/entry_points.txt
extinfo-0.0.8.dist-info/RECORD
