Metadata-Version: 2.1
Name: extinfo
Version: 0.0.8
Summary: Scrape information about file extensions from web sources
Home-page: https://pypi.org/project/extinfo
License: Apache 2.0
Author: Ryan Delaney
Author-email: ryan.patrick.delaney+git@proton.me
Requires-Python: >=3.10,<4.0
Classifier: Development Status :: 4 - Beta
Classifier: Environment :: Console
Classifier: License :: OSI Approved :: Apache Software License
Classifier: License :: Other/Proprietary License
Classifier: Programming Language :: Python :: 3
Classifier: Programming Language :: Python :: 3.10
Classifier: Programming Language :: Python :: 3.11
Classifier: Programming Language :: Python :: 3 :: Only
Requires-Dist: beautifulsoup4 (>=4.10.0,<5.0.0)
Requires-Dist: click (>=8.0.3,<9.0.0)
Requires-Dist: deal (>=4.19.1,<5.0.0)
Requires-Dist: requests (>=2.27.1,<3.0.0)
Requires-Dist: rich (>=12.2.0,<13.0.0)
Project-URL: Repository, https://github.com/rpdelaney/extinfo
